sidebar_menu/__init__.py
sidebar_menu/apps.py
sidebar_menu/templates/sidebar_menu/link.html
sidebar_menu/templates/sidebar_menu/plain.html
sidebar_menu/templates/sidebar_menu/root.html
sidebar_menu/templates/sidebar_menu/tree.html
django_sidebar_menu-0.1.0.dist-info/WHEEL
django_sidebar_menu-0.1.0.dist-info/METADATA
django_sidebar_menu-0.1.0.dist-info/RECORD
